finitelight/__init__.py
finitelight/finitelight.py
finitelight-0.0.1.dist-info/LICENSE
finitelight-0.0.1.dist-info/METADATA
finitelight-0.0.1.dist-info/WHEEL
finitelight-0.0.1.dist-info/top_level.txt
finitelight-0.0.1.dist-info/RECORD
