Metadata-Version: 2.1
Name: finitelight
Version: 0.0.1
Summary: A package for lightspeed calculations
Home-page: https://github.com/brobbins2001/finitelight
Author: Bryan Robbins
Author-email: btr1014@wildcats.unh.edu
License: UNKNOWN
Project-URL: Bug Tracker, https://github.com/brobbins2001/finitelight/issues
Platform: UNKNOWN
Classifier: Programming Language :: Python :: 3
Classifier: License :: OSI Approved :: MIT License
Classifier: Operating System :: OS Independent
Requires-Python: >=3.6
License-File: LICENSE
